{"Network": {"Technology": "GSM", "2G bands": "GSM 850 / 900 / 1800 / 1900 - SIM 1", "\u00a0": "GSM 850 / 900 / 1800 / 1900 - SIM 2 & SIM 3", "GPRS": "Class 10", "EDGE": "No"}, "Launch": {"Announced": "2011, August. Released 2011, September", "Status": "Discontinued"}, "Body": {"Dimensions": "106.5 x 59 x 14.6 mm (4.19 x 2.32 x 0.57 in)", "Weight": "-", "Keyboard": "QWERTY", "SIM": "Triple SIM (Mini-SIM)", "\u00a0": "Flashlight"}, "Display": {"Type": "TFT, 26K colors", "Size": "2.0 inches, 12.6 cm2 (~20.0% screen-to-body ratio)", "Resolution": "220 x 176 pixels (~141 ppi density)"}, "Memory": {"Card slot": "microSDHC (dedicated slot)", "Phonebook": "300 entries", "Call records": "Yes"}, "Main Camera": {"Single": "VGA", "Features": "LED flash", "Video": "Yes"}, "Selfie camera": {"Single": "Yes", "Video": ""}, "Sound": {"Loudspeaker ": "Yes", "3.5mm jack ": "Yes"}, "Comms": {"WLAN": "No", "Bluetooth": "Yes", "Positioning": "No", "Radio": "Stereo FM radio", "USB": "miniUSB (charging only)"}, "Features": {"Sensors": "", "Messaging": "SMS, MMS", "Games": "Yes", "Java": "No", "\u00a0": "TV app\r\nOrganizer\r\nMP4 player\r\nMP3 player\r\nPredictive text input\n"}, "Battery": {"Type": "Removable Li-Ion 1000 mAh battery", "Stand-by": "Up to 580 h", "Talk time": "Up to 8 h"}, "Misc": {"Colors": "Purple, Black, Red, Rose, Coffee, Blue, Yellow"}}