{"Network": {"Technology": "GSM / HSPA", "2G bands": "GSM 850 / 900 / 1800 / 1900 ", "3G bands": "HSDPA 900 / 1900 / 2100 ", "Speed": "HSPA 7.2/0.384 Mbps"}, "Launch": {"Announced": "2009, November. Released 2009, December", "Status": "Discontinued"}, "Body": {"Dimensions": "112.8 x 62.8 x 13.4 mm (4.44 x 2.47 x 0.53 in)", "Weight": "132 g (4.66 oz)", "Keyboard": "QWERTY", "SIM": "Mini-SIM"}, "Display": {"Type": "AMOLED resistive touchscreen, 256K colors (65K effective colors)", "Size": "2.5 inches, 19.4 cm2 (~27.3% screen-to-body ratio)", "Resolution": "320 x 240 pixels, 4:3 ratio (~160 ppi density)"}, "Platform": {"OS": "Microsoft Windows Mobile 6.5 Professional", "Chipset": "Qualcomm MSM7200", "CPU": "528 MHz ARM 11", "GPU": "Adreno 130"}, "Memory": {"Card slot": "microSDHC (dedicated slot)", "Internal": "256MB RAM, 512MB ROM"}, "Main Camera": {"Single": "3.15 MP, AF", "Video": "Yes"}, "Selfie camera": {"\u00a0": "No"}, "Sound": {"Loudspeaker ": "Yes", "3.5mm jack ": "Yes"}, "Comms": {"WLAN": "Wi-Fi 802.11b/g", "Bluetooth": "2.0, A2DP", "Positioning": "GPS, A-GPS", "Radio": "No", "USB": "microUSB 2.0"}, "Features": {"Sensors": "", "Browser": "WAP 2.0/xHTML, HTML", "\u00a0": "Pocket Office \r\nOrganizer\r\nMedia player\r\nVoice memo\r\nPredictive text input"}, "Battery": {"Type": "Removable Li-Po battery"}, "Misc": {"Colors": "Black", "SAR": "0.59 W/kg (head) \u00a0 \u00a0 1.08 W/kg (body) \u00a0 \u00a0 ", "Price": "About 140 EUR"}}