{"Network": {"Technology": "GSM / HSPA", "2G bands": "GSM 850 / 900 / 1800 / 1900 ", "3G bands": "HSDPA 900 / 2100 ", "Speed": "HSPA 3.6/0.384 Mbps"}, "Launch": {"Announced": "2010, October. Released 2010, October", "Status": "Discontinued"}, "Body": {"Dimensions": "109.5 x 55 x 11.9 mm (4.31 x 2.17 x 0.47 in)", "Weight": "100 g (3.53 oz)", "SIM": "Mini-SIM"}, "Display": {"Type": "TFT,  256K colors", "Size": "3.2 inches, 29.1 cm2 (~48.4% screen-to-body ratio)", "Resolution": "240 x 400 pixels, 5:3 ratio (~146 ppi density)", "\u00a0": "TouchWiz UI 3.0"}, "Platform": {"OS": "bada OS"}, "Memory": {"Card slot": "microSDHC (dedicated slot)", "Internal": "100MB"}, "Main Camera": {"Single": "3.15 MP", "Video": "Yes"}, "Selfie camera": {"\u00a0": "No"}, "Sound": {"Loudspeaker ": "Yes", "3.5mm jack ": "Yes"}, "Comms": {"WLAN": "Wi-Fi 802.11 b/g/n, hotspot", "Bluetooth": "3.0, A2DP", "Positioning": "GPS, A-GPS", "Radio": "Stereo FM radio, RDS", "USB": "microUSB 2.0"}, "Features": {"Sensors": "Accelerometer", "Browser": "WAP 2.0/xHTML, HTML", "\u00a0": "SNS integration\r\nMP3/WAV/eAAC+ player\r\nMP4/H.264 player\r\nMusic recognition\r\nOrganizer\r\nPhoto editor\r\nVoice memo\r\nPredictive text input (T9 Trace)"}, "Battery": {"Type": "Removable Li-Ion 1200 mAh battery"}, "Misc": {"Colors": "Black", "SAR": "0.69 W/kg (head) \u00a0 \u00a0 0.81 W/kg (body) \u00a0 \u00a0 ", "SAR EU": "0.70 W/kg (head) \u00a0 \u00a0 ", "Price": "About 120 EUR"}}