{"Network": {"Technology": "GSM / HSPA", "2G bands": "GSM 850 / 900 / 1800 / 1900 ", "3G bands": "HSDPA 900 / 2100 ", "Speed": "HSPA 3.6/0.384 Mbps"}, "Launch": {"Announced": "2009, June. Released 2009, September", "Status": "Discontinued"}, "Body": {"Dimensions": "107 x 51.8 x 12.9 mm (4.21 x 2.04 x 0.51 in)", "Weight": "103 g (3.63 oz)", "SIM": "Mini-SIM"}, "Display": {"Type": "TFT resistive touchscreen, 65K colors", "Size": "3.0 inches, 25.6 cm2 (~46.2% screen-to-body ratio)", "Resolution": "240 x 400 pixels, 5:3 ratio (~155 ppi density)", "\u00a0": "TouchWiz v2.0 UI"}, "Platform": {"OS": "Microsoft Windows Mobile 6.1 Professional, upgradable to Windows Mobile 6.5", "CPU": "800MHz ARM 1176"}, "Memory": {"Card slot": "microSDHC (dedicated slot)", "Internal": "250MB"}, "Main Camera": {"Single": "3.15 MP, AF", "Video": "480p@15fps"}, "Selfie camera": {"\u00a0": "Videocall camera"}, "Sound": {"Loudspeaker ": "Yes", "3.5mm jack ": "No"}, "Comms": {"WLAN": "Wi-Fi 802.11 b/g, DLNA", "Bluetooth": "2.1, A2DP", "Positioning": "GPS, A-GPS", "Radio": "Stereo FM radio, RDS and recording", "USB": "microUSB 2.0"}, "Features": {"Sensors": "Accelerometer", "Browser": "WAP 2.0/xHTML, HTML (Opera)", "\u00a0": "DviX/XviD/MP4/H.264/WMV9 player\r\nMP3/AAC/WMA player\r\nOrganizer\r\nPocket Office \r\nVoice memo\r\nPredictive text input"}, "Battery": {"Type": "Removable Li-Ion 1500 mAh battery", "Stand-by": "Up to 650 h", "Talk time": "Up to 9 h"}, "Misc": {"Colors": "Black, blue, red", "SAR": "0.74 W/kg (head) \u00a0 \u00a0 0.51 W/kg (body) \u00a0 \u00a0 ", "SAR EU": "0.79 W/kg (head) \u00a0 \u00a0 ", "Price": "About 150 EUR"}, "Tests": {"Camera": "\nPhoto", "Loudspeaker": "\nVoice 73dB / Noise 70dB / Ring 73dB\n", "Audio quality": "\nNoise -90.5dB / Crosstalk -82.8dB"}}