{"Network": {"Technology": "GSM / HSPA / LTE", "2G bands": "GSM 850 / 900 / 1800 / 1900 ", "3G bands": "HSDPA 850 / 900 / 1900 / 2100 ", "4G bands": "1, 2, 3, 4, 5, 7, 8, 17, 20", "Speed": "HSPA, LTE"}, "Launch": {"Announced": "2015, July. Released 2015, September", "Status": "Discontinued"}, "Body": {"Dimensions": "198.6 x 134.8 x 5.6 mm (7.82 x 5.31 x 0.22 in)", "Weight": "265 g (Wi-Fi) / 272 g (LTE) (9.35 oz)", "SIM": "Nano-SIM"}, "Display": {"Type": "Super AMOLED", "Size": "8.0 inches, 198.2 cm2 (~74.0% screen-to-body ratio)", "Resolution": "1536 x 2048 pixels, 4:3 ratio (~320 ppi density)"}, "Platform": {"OS": "Android 5.0.2 (Lollipop), upgradable to 6.0.1 (Marshmallow) - T710, T715Android 6.0.1 (Marshmallow), upgradable to 7.0 (Nougat) - T719N", "Chipset": "Exynos 5433 - T710, T715Qualcomm MSM8976 Snapdragon 652 (28 nm) - T719N", "CPU": "Octa-core (4x1.9 GHz & 4x1.3 GHz) - T710, T715Octa-core (4x1.8 GHz Cortex-A72 & 4x1.4 GHz Cortex-A53) - T719N", "GPU": "Mali-T760 MP6 - T710, T715Adreno 510 - T719N"}, "Memory": {"Card slot": "microSDXC (dedicated slot)", "Internal": "32GB 3GB RAM, 64GB 3GB RAM", "\u00a0": "eMMC 5.0 or eMMC 5.1"}, "Main Camera": {"Single": "8 MP, AF", "Video": "1440p@30fps"}, "Selfie camera": {"Single": "2.1 MP", "Video": ""}, "Sound": {"Loudspeaker ": "Yes", "3.5mm jack ": "Yes"}, "Comms": {"WLAN": "Wi-Fi 802.11 a/b/g/n/ac, dual-band, Wi-Fi Direct", "Bluetooth": "4.1, A2DP, LE", "Positioning": "GPS, GLONASS", "NFC": "No", "Radio": "No", "USB": "microUSB 2.0 (MHL TV-out)"}, "Features": {"Sensors": "Fingerprint (front-mounted), accelerometer, gyro, proximity, compass", "\u00a0": "ANT+"}, "Battery": {"Type": "Li-Ion 4000 mAh, non-removable", "Talk time": "Up to 27 h (3G)", "Music play": "Up to 74 h"}, "Misc": {"Colors": "White, black gold", "Models": "SM-T715, SM-T710, SM-T719N, SM-T719, SM-T715Y, SM-T719Y, SM-T713", "SAR": "0.96 W/kg (head) \u00a0 \u00a0 1.59 W/kg (body) \u00a0 \u00a0 ", "SAR EU": "0.34 W/kg (head) \u00a0 \u00a0 0.47 W/kg (body) \u00a0 \u00a0 ", "Price": "About 290 EUR"}}