{"Network": {"Technology": "GSM", "2G bands": "GSM 900 / 1800 / 1900 ", "GPRS": "Class 10", "EDGE": "Class 10"}, "Launch": {"Announced": "2008, February. Released 2008, February", "Status": "Discontinued"}, "Body": {"Dimensions": "99.5 x 48 x 14.8 mm (3.92 x 1.89 x 0.58 in)", "Weight": "92 g (3.25 oz)", "SIM": "Mini-SIM"}, "Display": {"Type": "TFT, 65K colors", "Size": "2.0 inches, 12.6 cm2 (~26.4% screen-to-body ratio)", "Resolution": "128 x 160 pixels (~102 ppi density)"}, "Memory": {"Card slot": "microSD (dedicated slot)", "Phonebook": "1000 entries, Photocall", "Call records": "20 dialed, 20 received, 20 missed calls", "Internal": "10MB"}, "Main Camera": {"Single": "1.3 MP", "Video": "Yes"}, "Selfie camera": {"\u00a0": "No"}, "Sound": {"Loudspeaker ": "Yes", "Alert types": "Vibration; Downloadable polyphonic, MP3 ringtones", "3.5mm jack ": "No"}, "Comms": {"WLAN": "No", "Bluetooth": "2.0, A2DP", "Positioning": "No", "Radio": "FM radio", "USB": "2.0"}, "Features": {"Sensors": "", "Messaging": "SMS, EMS, MMS", "Browser": "WAP 2.0/xHTML, HTML", "Games": "Yes", "Java": "Yes, MIDP 2.0", "\u00a0": "MP4/3GP player/recorder \r\nMP3/AAC/AAC+/MIDI player\r\nBT printing\r\nOrganizer\r\nCurrency converter\r\nVoice memo\r\nPredictive text input"}, "Battery": {"Type": "Removable Li-Ion 800 mAh battery", "Stand-by": "Up to 250 h", "Talk time": "Up to 3 h"}, "Misc": {"Colors": "Black, Pink", "SAR": "0.38 W/kg (head) \u00a0 \u00a0 0.89 W/kg (body) \u00a0 \u00a0 ", "SAR EU": "0.50 W/kg (head) \u00a0 \u00a0 ", "Price": "About 60 EUR"}}