{"Network": {"Technology": "GSM", "2G bands": "GSM 850 / 900 / 1800 / 1900 ", "\u00a0": "GSM 850 / 900 / 1800 / 1900 - SIM 2 & SIM 3 (P730 only)", "GPRS": "Yes", "EDGE": "Yes"}, "Launch": {"Announced": "2012, June. Released 2012, Q4", "Status": "Discontinued"}, "Body": {"Dimensions": "105.5 x 59 x 12.9 mm (4.15 x 2.32 x 0.51 in)", "Weight": "90 g without battery (3.17 oz)", "Keyboard": "QWERTY", "SIM": "Triple SIM (Mini-SIM)", "\u00a0": "Flashlight"}, "Display": {"Type": "TFT, 65K colors", "Size": "2.3 inches, 16.4 cm2 (~26.3% screen-to-body ratio)", "Resolution": "320 x 240 pixels, 4:3 ratio (~174 ppi density)"}, "Memory": {"Card slot": "microSDHC (dedicated slot)", "Phonebook": "Yes", "Call records": "Yes", "Internal": "128Mb 64Mb RAM"}, "Main Camera": {"Single": "2 MP", "Features": "LED flash", "Video": "Yes"}, "Selfie camera": {"\u00a0": "No"}, "Sound": {"Loudspeaker ": "Yes", "3.5mm jack ": "Yes"}, "Comms": {"WLAN": "Wi-Fi 802.11 a/b/g", "Bluetooth": "2.1, A2DP", "Positioning": "No", "NFC": "No", "Radio": "Stereo FM radio", "USB": "microUSB"}, "Features": {"Sensors": "", "Messaging": "SMS, MMS", "Games": "Yes", "Java": "Yes", "\u00a0": "Analog TV\r\nFacebook\r\nMusic player\r\nVideo player\r\nOrganizer\r\nVoice memo"}, "Battery": {"Type": "Li-Ion 800 mAh, removable", "Stand-by": "Up to 280 h", "Talk time": "Up to 7 h"}, "Misc": {"Colors": "Black"}}