{"Network": {"Technology": "GSM", "2G bands": "GSM 900 / 1800 / 1900 ", "GPRS": "Class 10", "EDGE": "No"}, "Launch": {"Announced": "2005", "Status": "Discontinued"}, "Body": {"Dimensions": "105 x 44 x 15.9 mm (4.13 x 1.73 x 0.63 in)", "Weight": "73 g (2.57 oz)", "SIM": "Mini-SIM"}, "Display": {"Type": "CSTN, 65K colors", "Size": "1.6 inches, 8.3 cm2 (~17.9% screen-to-body ratio)", "Resolution": "128 x 128 pixels, 1:1 ratio (~113 ppi density)", "\u00a0": "Downloadable wallpapers"}, "Memory": {"Card slot": "No", "Phonebook": "200 x 6 fields, 7 groups", "Call records": "15 dialed, 15 received, 15 missed calls", "Internal": "1.3MB", "\u00a0": "20 calendar items"}, "Main Camera": {"Single": "VGA", "Video": "No"}, "Selfie camera": {"\u00a0": "No"}, "Sound": {"Loudspeaker ": "No", "Alert types": "Vibration; Downloadable polyphonic ringtones", "3.5mm jack ": "No"}, "Comms": {"WLAN": "No", "Bluetooth": "No", "Positioning": "No", "Radio": "No", "USB": "Proprietary"}, "Features": {"Sensors": "", "Messaging": "SMS, EMS, MMS", "Browser": "WAP 2.0/xHTML", "Games": "2 + downloadable", "Java": "Yes", "\u00a0": "Predictive text input\r\nOrganizer\r\nVoice memo\r\nModem "}, "Battery": {"Type": "Removable Li-Ion battery", "Stand-by": "Up to 200 h"}, "Misc": {"Colors": ""}}