{"Network": {"Technology": "GSM / HSPA", "2G bands": "GSM 900 / 1800 / 1900 ", "3G bands": "HSDPA 2100 ", "Speed": "HSPA 7.2/0.384 Mbps"}, "Launch": {"Announced": "2008, September. Released 2008, December", "Status": "Discontinued"}, "Body": {"Dimensions": "108 x 54 x 13 mm (4.25 x 2.13 x 0.51 in)", "Weight": "109 g (3.84 oz)", "SIM": "Mini-SIM"}, "Display": {"Type": "TFT resistive touchscreen, 256K colors", "Size": "3.0 inches, 25.6 cm2 (~43.9% screen-to-body ratio)", "Resolution": "240 x 400 pixels, 5:3 ratio (~155 ppi density)", "\u00a0": "Flash UI\r\nDownloadable wallpapers"}, "Memory": {"Card slot": "microSDHC (dedicated slot)", "Phonebook": "Yes, Photocall", "Call records": "40 dialed, 40 received, 40 missed calls", "Internal": "100MB"}, "Main Camera": {"Single": "3.15 MP, AF", "Video": "320p"}, "Selfie camera": {"\u00a0": "Videocall camera"}, "Sound": {"Loudspeaker ": "Yes", "3.5mm jack ": "No"}, "Comms": {"WLAN": "No", "Bluetooth": "2.0, A2DP", "Positioning": "No", "Radio": "No", "USB": "2.0"}, "Features": {"Sensors": "", "Messaging": "SMS, EMS, MMS, Email", "Browser": "WAP 2.0/xHTML, HTML", "Games": "Yes", "Java": "Yes, MIDP 2.0", "\u00a0": "DVB-H or DVB-T TV receiver (country specific)\r\nTV-out \r\nMP3/MP4/DivX/Xvid player\r\nOrganizer\r\nDocument viewer (Word, Excel, PowerPoint, PDF)\r\nVoice memo\r\nPredictive text input"}, "Battery": {"Type": "Removable Li-Ion 1000 mAh battery", "Stand-by": "Up to 300 h", "Talk time": "Up to 4 h"}, "Misc": {"Colors": "Black", "SAR": "0.86 W/kg (head) \u00a0 \u00a0 0.52 W/kg (body) \u00a0 \u00a0 ", "Price": "About 150 EUR"}}