{"Network": {"Technology": "GSM", "2G bands": "GSM 850 / 900 / 1800 / 1900 - SIM 1 & SIM 2", "GPRS": "Yes", "EDGE": "Yes"}, "Launch": {"Announced": "2013. Released 2013", "Status": "Discontinued"}, "Body": {"Dimensions": "125 x 57 x 22 mm (4.92 x 2.24 x 0.87 in)", "Weight": "161 g (5.68 oz)", "SIM": "Dual SIM", "\u00a0": "IP67 dust/water resistant (up to 1m for 30 mins)\r\nDrop-to-concrete resistance from up to 1.8m\r\nFlashlight"}, "Display": {"Type": "TFT", "Size": "2.0 inches, 12.4 cm2 (~17.4% screen-to-body ratio)", "Resolution": "240 x 320 pixels, 4:3 ratio (~200 ppi density)"}, "Platform": {"Chipset": "Mediatek MT6235", "CPU": "208 MHz"}, "Memory": {"Card slot": "microSDHC (dedicated slot)", "Phonebook": "Yes", "Call records": "Yes"}, "Main Camera": {"Single": "2 MP, AF", "Video": "Yes"}, "Selfie camera": {"\u00a0": "No"}, "Sound": {"Loudspeaker ": "Yes", "3.5mm jack ": "Yes"}, "Comms": {"WLAN": "No", "Bluetooth": "2.1", "Positioning": "No", "NFC": "No", "Radio": "FM radio", "USB": "microUSB 2.0"}, "Features": {"Sensors": "", "Messaging": "SMS", "Games": "No", "Java": ""}, "Battery": {"Type": "Li-Ion 1300 mAh, removable", "Stand-by": "Up to 156 h", "Talk time": "Up to 9 h 30 min"}, "Misc": {"Colors": "Black", "Price": "About 140 EUR"}}