{"i858": ["i_mobile_i858-3327.php", "i-mobile i858 Android smartphone", "Announced  2010", "4.3\u2033  display", " 5 MP primary camera", " 1500 mAh battery"], "8500": ["i_mobile_8500-3328.php", "i-mobile 8500 Android smartphone", "Announced  2010", "3.2\u2033  display", " 5 MP primary camera", " 1500 mAh battery", " 128 MB RAM"], "5230": ["i_mobile_5230-3329.php", "i-mobile 5230 phone", "Announced  2010", "2.8\u2033  display", " 5 MP primary camera", " 1200 mAh battery", " 48 MB storage"], "Hitz 2206": ["i_mobile_hitz_2206-3331.php", "i-mobile Hitz 2206 phone", "Announced  2010", "TFT", " 65K colors display", " 1000 mAh battery"], "5220": ["i_mobile_5220-3330.php", "i-mobile 5220 phone", "Announced  2010", "2.4\u2033  display", " 5 MP primary camera", " 1100 mAh battery"], "TV658 Touch&Move": ["i_mobile_tv658_touch&move-2974.php", "i-mobile TV658 Touch&Move phone", "Announced Oct 2009", "3.0\u2033  display", " 8 MP primary camera", " 1050 mAh battery"], "Hitz 212": ["i_mobile_hitz_212-2972.php", "i-mobile Hitz 212 phone", "Announced Oct 2009", "1.77\u2033  display", " 750 mAh battery"], "Hitz 210": ["i_mobile_hitz_210-2971.php", "i-mobile Hitz 210 phone", "Announced Oct 2009", "1.8\u2033  display", " 700 mAh battery"], "TV650 Touch": ["i_mobile_tv650_touch-2878.php", "i-mobile TV650 Touch phone", "Announced Jul 2009", "3.0\u2033  display", " 3.15 MP primary camera", " 1000 mAh battery"], "TV550 Touch": ["i_mobile_tv550_touch-2877.php", "i-mobile TV550 Touch phone", "Announced Jul 2009", "2.8\u2033  display", " 1000 mAh battery"], "TV 630": ["i_mobile_tv_630-2875.php", "i-mobile TV 630 phone", "Announced Jul 2009", "2.4\u2033  display", " 8 MP primary camera", " 1100 mAh battery"], "TV 628": ["i_mobile_tv_628-2874.php", "i-mobile TV 628 phone", "Announced Jul 2009", "2.4\u2033  display", " 3.15 MP primary camera", " 950 mAh battery", " 10 MB storage"], "TV 620": ["i_mobile_tv_620-2873.php", "i-mobile TV 620 phone", "Announced Jul 2009", "2.4\u2033  display", " 3.15 MP primary camera", " 1050 mAh battery", " 14 MB storage"], "TV 536": ["i_mobile_tv_536-2872.php", "i-mobile TV 536 phone", "Announced Jul 2009", "2.4\u2033  display", " 1000 mAh battery"], "638CG": ["i_mobile_638cg-2876.php", "i-mobile 638CG phone", "Announced Jul 2009", "2.4\u2033  display", " 3.15 MP primary camera", " 1050 mAh battery", " 25 MB storage"], "Hitz 232CG": ["i_mobile_hitz_232cg-2871.php", "i-mobile Hitz 232CG phone", "Announced Jul 2009", "2.0\u2033  display", " 1050 mAh battery"], "TV 535": ["i_mobile_tv_535-2680.php", "i-mobile TV 535 phone", "Announced Jan 2009", "2.2\u2033  display", " 1.3 MP primary camera", " 1000 mAh battery"], "627": ["i_mobile_627-2681.php", "i-mobile 627 phone", "Announced Oct 2008", "2.0\u2033  display", " 3.15 MP primary camera", " 830 mAh battery", " 63 MB storage"], "TV 533": ["i_mobile_tv_533-2679.php", "i-mobile TV 533 phone", "Announced Jan 2009", "2.4\u2033  display", " 1100 mAh battery"], "TV 530": ["i_mobile_tv_530-2678.php", "i-mobile TV 530 phone", "Announced Sep 2008", "2.4\u2033  display", " 1100 mAh battery"], "TV 523": ["i_mobile_tv_523-2597.php", "i-mobile TV 523 phone", "Announced Oct 2008", "2.2\u2033  display", " 1000 mAh battery"], "522": ["i_mobile_522-2596.php", "i-mobile 522 phone", "Announced Oct 2008", "2.2\u2033  display", " 1000 mAh battery", " 120 MB storage"], "320": ["i_mobile_320-2677.php", "i-mobile 320 phone", "Announced Oct 2008", "2.2\u2033  display", " 750 mAh battery"], "319": ["i_mobile_319-2595.php", "i-mobile 319 phone", "Announced Sep 2008", "1.67\u2033  display", " 830 mAh battery", " 50 MB storage"], "TV 626": ["i_mobile_tv_626-2477.php", "i-mobile TV 626 phone", "Announced Jul 2008", "2.4\u2033  display", " 3.15 MP primary camera", " 1000 mAh battery", " 87 MB storage"], "902": ["i_mobile_902-2421.php", "i-mobile 902 phone", "Announced Oct 2007", "2.0\u2033  display", " 5 MP primary camera", " 1100 mAh battery", " 128 MB storage"], "625": ["i_mobile_625-2401.php", "i-mobile 625 phone", "Announced May 2008", "2.0\u2033  display", " 3.15 MP primary camera", " 830 mAh battery", " 60 MB storage"], "903": ["i_mobile_903-2402.php", "i-mobile 903 phone", "Announced May 2007", "2.0\u2033  display", " 2 MP primary camera", " 850 mAh battery", " 64 MB storage"], "613": ["i_mobile_613-2400.php", "i-mobile 613 phone", "Announced Dec 2007", "2.2\u2033  display", " 3.15 MP primary camera", " 1000 mAh battery", " 87 MB storage"], "520": ["i_mobile_520-2399.php", "i-mobile 520 phone", "Announced Dec 2007", "1.76\u2033  display", " 1.3 MP primary camera", " 750 mAh battery", " 56 MB storage"], "518": ["i_mobile_518-2398.php", "i-mobile 518 phone", "Announced Dec 2007", "2.0\u2033  display", " 2 MP primary camera", " 1000 mAh battery", " 88 MB storage"], "510": ["i_mobile_510-2397.php", "i-mobile 510 phone", "Announced Apr 2006", "TFT", " 256K colors display", " 720 mAh battery", " 64 MB storage"], "318": ["i_mobile_318-2396.php", "i-mobile 318 phone", "Announced Mar 2008", "1.8\u2033  display", " 700 mAh battery", " 120 MB storage"], "315": ["i_mobile_315-2395.php", "i-mobile 315 phone", "Announced Nov 2007", "1.5\u2033  display", " 720 mAh battery"], "202": ["i_mobile_202-2676.php", "i-mobile 202 phone", "Announced Nov 2008", "1.8\u2033  display", " 750 mAh battery"], "201": ["i_mobile_201-2394.php", "i-mobile 201 phone", "Announced May 2008", "1.5\u2033  display", " 750 mAh battery"], "101": ["i_mobile_101-2393.php", "i-mobile 101 phone", "Announced May 2008", "1.5\u2033  display", " 680 mAh battery"]}