{"Network": {"Technology": "GSM", "2G bands": "GSM 900 / 1800 / 1900 ", "GPRS": "Yes", "EDGE": "No"}, "Launch": {"Announced": "2004, Q1", "Status": "Discontinued"}, "Body": {"Dimensions": "87 x 46 x 26 mm (3.43 x 1.81 x 1.02 in)", "Weight": "88 g (3.10 oz)", "SIM": "Mini-SIM"}, "Display": {"Type": "TFT, 256K colors", "Size": "", "Resolution": "128 x 160 pixels, 11 lines", "\u00a0": "Second external display, STN, 65K colors (96 x 64 pixels)\r\n7 color optic fiberlighting\r\n3 color keypad backlighting\r\nScreensavers and wallpapers"}, "Memory": {"Card slot": "No", "Phonebook": "500 entries, contact groups, Photo call", "Call records": "20 received, dialed and missed calls", "Internal": "4MB"}, "Main Camera": {"Single": "VGA", "Video": "Yes"}, "Selfie camera": {"\u00a0": "No"}, "Sound": {"Loudspeaker ": "Yes", "Alert types": "Vibration; Downloadable polyphonic, MP3 ringtones, composer", "3.5mm jack ": "No"}, "Comms": {"WLAN": "No", "Bluetooth": "No", "Positioning": "No", "Radio": "No", "USB": ""}, "Features": {"Sensors": "", "Messaging": "SMS, MMS, Email", "Browser": "WAP", "Games": "Yes + downloadable", "Java": "No", "\u00a0": "Predictive text input (iTAP)\r\nBio-rhythm\r\nStopwatch\r\nCalculator\r\nVoice memo"}, "Battery": {"Type": "Removable Li-Ion 680 mAh battery", "Stand-by": "Up to 100 h", "Talk time": "Up to 6 h"}, "Misc": {"Colors": "Pearl White, Silver"}}