{"Network": {"Technology": "GSM / HSPA", "2G bands": "GSM 850 / 900 / 1800 / 1900 ", "3G bands": "HSDPA 850 / 1900 / 2100 ", "\u00a0": "HSDPA 900 / 1700 / 2100 ", "Speed": "HSPA 7.2/2 Mbps"}, "Launch": {"Announced": "2011, August. Released 2011, August", "Status": "Discontinued"}, "Body": {"Dimensions": "109 x 60 x 11 mm (4.29 x 2.36 x 0.43 in)", "Weight": "99 g (3.49 oz)", "Keyboard": "QWERTY", "SIM": "Mini-SIM", "\u00a0": "Optical trackpad"}, "Display": {"Type": "TFT", "Size": "2.44 inches, 18.4 cm2 (~28.2% screen-to-body ratio)", "Resolution": "480 x 360 pixels, 4:3 ratio (~246 ppi density)"}, "Platform": {"OS": "BlackBerry OS 7.0", "CPU": "800MHz"}, "Memory": {"Card slot": "microSDHC (dedicated slot)", "Internal": "512MB 512MB RAM"}, "Main Camera": {"Single": "5 MP", "Features": "LED flash", "Video": "480p"}, "Selfie camera": {"\u00a0": "No"}, "Sound": {"Loudspeaker ": "Yes", "3.5mm jack ": "Yes"}, "Comms": {"WLAN": "Wi-Fi 802.11 b/g/n, UMA (carrier-dependent)", "Bluetooth": "2.1, A2DP", "Positioning": "GPS, A-GPS", "NFC": "Yes", "Radio": "No", "USB": "microUSB 2.0"}, "Features": {"Sensors": "", "Browser": "HTML", "\u00a0": "MP3/eAAC+/WMA/WAV/FLAC player\r\nMP4/H.264/WMV player\r\nOrganizer\r\nDocument viewer\r\nVoice memo/dial\r\nPredictive text input"}, "Battery": {"Type": "Removable Li-Ion 1000 mAh battery", "Stand-by": "Up to 336 h (2G) / Up to 288 h (3G)", "Talk time": "Up to 5 h (2G) / Up to 5 h (3G)", "Music play": "Up to 25 h"}, "Misc": {"Colors": "Black, Purple, Pink", "SAR": "1.42 W/kg (head) \u00a0 \u00a0 1.06 W/kg (body) \u00a0 \u00a0 ", "SAR EU": "1.22 W/kg (head) \u00a0 \u00a0 0.62 W/kg (body) \u00a0 \u00a0 ", "Price": "About 90 EUR"}, "Tests": {"Display": "\nContrast ratio: 1054:1 (nominal)", "Camera": "\nPhoto", "Loudspeaker": "\nVoice 69dB / Noise 65dB / Ring 71dB\n", "Audio quality": "\nNoise -85.9dB / Crosstalk -82.1dB"}}