{"Network": {"Technology": "GSM / HSPA", "2G bands": "GSM 850 / 900 / 1800 / 1900 ", "3G bands": "HSDPA 900 / 2100 ", "Speed": "HSPA"}, "Launch": {"Announced": "2013. Released 2013", "Status": "Discontinued"}, "Body": {"Dimensions": "123 x 63.5 x 11.2 mm (4.84 x 2.5 x 0.44 in)", "Weight": "-", "SIM": "Dual SIM (Dual stand-by)"}, "Display": {"Type": "TFT", "Size": "3.95 inches, 46.5 cm2 (~59.5% screen-to-body ratio)", "Resolution": "320 x 480 pixels, 3:2 ratio (~146 ppi density)"}, "Platform": {"OS": "Android 4.0 (Ice Cream Sandwich)", "CPU": "1.0 GHz Cotex-A9"}, "Memory": {"Card slot": "microSDHC (dedicated slot)", "Internal": "4GB 512MB RAM"}, "Main Camera": {"Single": "2 MP", "Video": "Yes"}, "Selfie camera": {"Single": "VGA", "Video": ""}, "Sound": {"Loudspeaker ": "Yes", "3.5mm jack ": "Yes"}, "Comms": {"WLAN": "Wi-Fi 802.11 b/g/n, hotspot", "Bluetooth": "4.0, A2DP", "Positioning": "GPS", "NFC": "No", "Radio": "FM radio", "USB": "microUSB"}, "Features": {"Sensors": "Accelerometer, proximity, compass"}, "Battery": {"Type": "Li-Ion 1700 mAh, removable"}, "Misc": {"Colors": "Cofee/Black", "SAR": "1.29 W/kg (head) \u00a0 \u00a0 0.83 W/kg (body) \u00a0 \u00a0 ", "Price": "About 90 EUR"}}