{"Network": {"Technology": "GSM", "2G bands": "GSM 900 / 1800 / 1900 ", "GPRS": "Class 8", "EDGE": "No"}, "Launch": {"Announced": "2001", "Status": "Discontinued"}, "Body": {"Dimensions": "84 x 44 x 21 mm (3.31 x 1.73 x 0.83 in)", "Weight": "79 g (2.79 oz)", "SIM": "Mini-SIM"}, "Display": {"Type": "Monochrome graphic, Optimax", "Size": "", "Resolution": "96 x 54 pixels, 5 lines, 16:9 ratio", "\u00a0": "Fixed icons"}, "Memory": {"Card slot": "No", "Phonebook": "1000", "Call records": "10 dialed, 10 received, 10 missed calls", "\u00a0": "1 MB memory for Java apps\r\n25 phone book voice tags\r\n9 quick access voice tags"}, "Camera": {"\u00a0": "No"}, "Sound": {"Loudspeaker ": "No", "Alert types": "Vibration; Downloadable monophonic ringtones", "3.5mm jack ": "No"}, "Comms": {"WLAN": "No", "Bluetooth": "No", "Positioning": "No", "Radio": "No", "USB": ""}, "Features": {"Sensors": "", "Messaging": "SMS, EMS", "Browser": "WAP 1.2.1", "Clock": "Yes", "Alarm": "No", "Games": "5 - Paddle Ball, Mind Blaster, Falling Numbers, Video Pocker and Black Jack + Java", "Java": "Yes", "\u00a0": "Predictive text input (iTAP)\r\nOrganizer\r\nVoice memo\r\nVoice dial"}, "Battery": {"Type": "Removable Li-Ion 500 mAh battery", "Stand-by": "up to 120 h", "Talk time": "up to 3 h"}, "Misc": {"Colors": "3"}}