{"Network": {"Technology": "GSM / HSPA / LTE / 5G", "2G bands": "GSM 850 / 900 / 1800 / 1900 - SIM 1 & SIM 2", "3G bands": "HSDPA 850 / 900 / 1800 / 1900 / 2100 ", "4G bands": "1, 2, 3, 4, 5, 7, 8, 12, 17, 34, 38, 39, 40, 41", "5G bands": "1, 3, 5, 7, 8, 20, 28, 38, 41, 78 SA/NSA/Sub6", "Speed": "HSPA, LTE-A (CA), 5G"}, "Launch": {"Announced": "2021, December 09", "Status": "Available. Released 2021, December 15"}, "Body": {"Dimensions": "163.6 x 75.6 x 8.5 mm (6.44 x 2.98 x 0.33 in)", "Weight": "194 g (6.84 oz)", "Build": "Glass front, glass back (Gorilla Glass 5)", "SIM": "Dual SIM (Nano-SIM, dual stand-by)", "\u00a0": "Water-repellent design"}, "Display": {"Type": "OLED, 1B colors, 144Hz, HDR10+, 500 nits (typ), 700 nits (HBM)", "Size": "6.7 inches, 108.4 cm2 (~87.6% screen-to-body ratio)", "Resolution": "1080 x 2400 pixels, 20:9 ratio (~393 ppi density)"}, "Platform": {"OS": "Android 12, MYUI 3.0", "Chipset": "Qualcomm SM8450 Snapdragon 8 Gen 1 (4 nm)", "CPU": "Octa-core (1x3.00 GHz Cortex-X2 & 3x2.50 GHz Cortex-A710 & 4x1.80 GHz Cortex-A510)", "GPU": "Adreno 730"}, "Memory": {"Card slot": "No", "Internal": "128GB 8GB RAM, 256GB 8GB RAM, 256GB 12GB RAM", "\u00a0": "UFS 3.1"}, "Main Camera": {"Triple": "50 MP, f/1.9, (wide), 1/1.55\", 1.0\u00b5m, Dual Pixel PDAF, OIS\r\n50 MP, f/2.2, 114\u02da (ultrawide), 1/2.76\", 0.64\u00b5m\r\n2 MP, f/2.4, (depth)", "Features": "Dual-LED flash, panorama, HDR", "Video": "4K@30fps, 1080p@30/60/120/240fps, 720p@960fps, 10-bit HDR10+, gyro-EIS"}, "Selfie camera": {"Single": "60 MP, f/2.2, (wide), 1/2.8\", 0.61\u00b5m\r\nor\r\n60 MP, f/2.2, (wide), 1/2.8\", 0.61\u00b5m, under display", "Features": "HDR", "Video": "4K@30fps, 1080p@30/120fps"}, "Sound": {"Loudspeaker ": "Yes, with stereo speakers", "3.5mm jack ": "No"}, "Comms": {"WLAN": "Wi-Fi 802.11 a/b/g/n/ac/6e, dual-band, Wi-Fi Direct", "Bluetooth": "5.2, A2DP, LE", "Positioning": "GPS (L1+L5), GLONASS, BDS, GALILEO", "NFC": "Yes", "Radio": "No", "USB": "USB Type-C"}, "Features": {"Sensors": "Fingerprint (side-mounted), accelerometer, gyro, proximity, compass", "\u00a0": "Ready For support"}, "Battery": {"Type": "Li-Po 5000 mAh (regular version)/ 4800 mAh (under screen camera version), non-removable", "Charging": "68W wired, 100% in 35 min (advertised)"}, "Misc": {"Colors": "White, Black", "Models": "XT2201-2, XT2201-6", "Price": "About 420 EUR"}}