{"Network": {"Technology": "No cellular connectivity", "2G bands": " N/A", "GPRS": "No", "EDGE": "No"}, "Launch": {"Announced": "2015, March. Released 2015, September", "Status": "Discontinued"}, "Body": {"Dimensions": "42 x 42 x 11.3 mm (1.65 x 1.65 x 0.44 in)", "Weight": "60.5 g (2.15 oz)", "Build": "Glass front (Sapphire crystal), stainless steel 316L frame", "SIM": "No", "\u00a0": "IP67 dust/water resistant (up to 1m for 30 mins)\r\nCompatible with standard 18mm straps"}, "Display": {"Type": "OLED", "Size": "1.4 inches", "Resolution": "400 x 400 pixels (~286 ppi density)", "Protection": "Sapphire crystal glass", "\u00a0": "Always-on screen"}, "Platform": {"OS": "Android Wear OS 2.1", "Chipset": "Qualcomm MSM8926 Snapdragon 400 (28 nm)", "CPU": "Quad-core 1.2 GHz Cortex-A7", "GPU": "Adreno 305"}, "Memory": {"Card slot": "No", "Internal": "4GB 512MB RAM", "\u00a0": "eMMC 4.5"}, "Camera": {"\u00a0": "No"}, "Sound": {"Loudspeaker ": "Yes", "3.5mm jack ": "No"}, "Comms": {"WLAN": "Wi-Fi 802.11 b/g", "Bluetooth": "4.1, LE", "Positioning": "No", "NFC": "No", "Radio": "No", "USB": "No"}, "Features": {"Sensors": "Accelerometer, gyro, heart rate, barometer", "\u00a0": "MP3 player\r\nPhoto viewer\r\nVoice dial/commands"}, "Battery": {"Type": "Li-Ion 300 mAh, non-removable", "Charging": "10W wired"}, "Misc": {"Colors": "Silver, Black, Rose Gold/ Black Leather, Steel Link Bracelet, Stainless Steel Mesh, Black-plated Link Bracelet, Alligator-pressed Brown Leather, Rose Gold-plated Link Bracelet, Wat", "Price": "About 290 EUR"}}